{
  "_export": {
    "schemaVersion": "1.0.0",
    "kind": "entities",
    "subject": "Able.cz s.r.o.",
    "ico": "24278815",
    "evidenceCutoff": "2026-07-17",
    "generatedAt": "2026-07-17",
    "source": "data/dossier/able/dossier.json",
    "note": "Public-source review. Derived losslessly from the dossier data; nothing added.",
    "count": 41
  },
  "entities": [
    {
      "id": "able",
      "label": "Able.cz s.r.o.",
      "type": "subject"
    },
    {
      "id": "faraga",
      "label": "V. Faraga",
      "type": "person"
    },
    {
      "id": "melicharek",
      "label": "T. Melichárek",
      "type": "person"
    },
    {
      "id": "blackfish",
      "label": "Blackfish",
      "type": "entity"
    },
    {
      "id": "schlesinger",
      "label": "V. Schlesinger",
      "type": "person"
    },
    {
      "id": "juhanak",
      "label": "R. Juhaňák",
      "type": "person"
    },
    {
      "id": "polansky",
      "label": "L. Polanský",
      "type": "person"
    },
    {
      "id": "zenx",
      "label": "ZenX Capital a.s.",
      "type": "investor"
    },
    {
      "id": "g5326",
      "label": "5326G s.r.o.",
      "type": "investor"
    },
    {
      "id": "pointfm",
      "label": "Point FM (M. Kříž)",
      "type": "investor"
    },
    {
      "id": "grolig",
      "label": "L. Grolig",
      "type": "person"
    },
    {
      "id": "domain",
      "label": "able.cz",
      "type": "domain"
    },
    {
      "id": "ksbr",
      "label": "Krajský soud v Brně",
      "type": "legal"
    },
    {
      "id": "hosting",
      "label": "Websupport (DNS/hosting)",
      "type": "domain"
    },
    {
      "id": "gwork",
      "label": "Google Workspace (email)",
      "type": "domain"
    },
    {
      "id": "tls",
      "label": "Let's Encrypt (TLS)",
      "type": "domain"
    },
    {
      "id": "aaa",
      "label": "AAA Auto",
      "type": "client"
    },
    {
      "id": "aures",
      "label": "Aures Holdings",
      "type": "client"
    },
    {
      "id": "arkadia",
      "label": "Arkadia",
      "type": "client"
    },
    {
      "id": "encall",
      "label": "Encall",
      "type": "client"
    },
    {
      "id": "tastetown",
      "label": "Taste Town",
      "type": "client"
    },
    {
      "id": "petr_faraga",
      "label": "P. Faraga",
      "type": "person"
    },
    {
      "id": "jakub_kaman",
      "label": "J. Kaman",
      "type": "person"
    },
    {
      "id": "ondrej_kaman",
      "label": "O. Kaman",
      "type": "person"
    },
    {
      "id": "oslzla",
      "label": "L. Oslzla",
      "type": "person"
    },
    {
      "id": "mindee",
      "label": "Mindee app s.r.o.",
      "type": "entity"
    },
    {
      "id": "era25",
      "label": "ERA25 s.r.o.",
      "type": "entity"
    },
    {
      "id": "verzuz",
      "label": "Verzuz.com s.r.o.",
      "type": "entity"
    },
    {
      "id": "fame_logistics",
      "label": "FaMe logistics s.r.o. (v likvidaci)",
      "type": "entity"
    },
    {
      "id": "fame_trade",
      "label": "FaMe trade s.r.o.",
      "type": "entity"
    },
    {
      "id": "fama_media",
      "label": "FaMa Media s.r.o.",
      "type": "entity"
    },
    {
      "id": "mmplan",
      "label": "M&M plan s.r.o.",
      "type": "entity"
    },
    {
      "id": "onelabel",
      "label": "one label s.r.o.",
      "type": "entity"
    },
    {
      "id": "bgo",
      "label": "BGO s.r.o.",
      "type": "entity"
    },
    {
      "id": "usporix",
      "label": "Usporix, s.r.o.",
      "type": "entity"
    },
    {
      "id": "verasto",
      "label": "VERASTO s.r.o.",
      "type": "entity"
    },
    {
      "id": "ventoux",
      "label": "Ventoux Studio s.r.o.",
      "type": "entity"
    },
    {
      "id": "schlesinger_sro",
      "label": "Vít Schlesinger s.r.o.",
      "type": "entity"
    },
    {
      "id": "artstay_lovs",
      "label": "Artstay / Lovs & Co. s.r.o.",
      "type": "entity"
    },
    {
      "id": "mysasy",
      "label": "mySASY a.s.",
      "type": "entity"
    },
    {
      "id": "exekuce-melicharek",
      "label": "Exekuce (podíl, 219 EX 00241/26)",
      "type": "legal"
    }
  ]
}
