{"ico":"06116159","obchodniJmeno":"VERASTO s.r.o.","sidlo":{"kodStatu":"CZ","nazevStatu":"Česká republika","kodKraje":116,"nazevKraje":"Jihomoravský kraj","kodOkresu":3713,"nazevOkresu":"Znojmo","kodObce":594920,"nazevObce":"Tasovice","cisloDomovni":275,"kodCastiObce":165123,"nazevCastiObce":"Tasovice","kodAdresnihoMista":10932305,"psc":67125,"textovaAdresa":"č.p. 275, 67125 Tasovice","standardizaceAdresy":true,"typCisloDomovni":1},"pravniForma":"112","pravniFormaRos":"112","financniUrad":"346","datumVzniku":"2017-05-18","datumAktualizace":"2024-05-13","dic":"CZ06116159","icoId":"06116159","adresaDorucovaci":{"radekAdresy1":"č.p. 275","radekAdresy2":"67125 Tasovice"},"czNace2008":["00","25","256","28","33","46","461","47","4941","5819","6820","6920","73","7410","7420","749","7729","8211","855","952"],"seznamRegistraci":{"stavZdrojeRos":"AKTIVNI","stavZdrojeVr":"AKTIVNI","stavZdrojeRes":"AKTIVNI","stavZdrojeRzp":"AKTIVNI","stavZdrojeNrpzs":"NEEXISTUJICI","stavZdrojeRpsh":"NEEXISTUJICI","stavZdrojeRcns":"NEEXISTUJICI","stavZdrojeSzr":"NEEXISTUJICI","stavZdrojeDph":"AKTIVNI","stavZdrojeSkDph":"NEEXISTUJICI","stavZdrojeSd":"NEEXISTUJICI","stavZdrojeIr":"NEEXISTUJICI","stavZdrojeCeu":"NEEXISTUJICI","stavZdrojeRs":"NEEXISTUJICI","stavZdrojeRed":"NEEXISTUJICI","stavZdrojeMonitor":"NEEXISTUJICI"},"primarniZdroj":"ros","dalsiUdaje":[{"obchodniJmeno":[{"obchodniJmeno":"VERASTO s.r.o.","primarniZaznam":true}],"sidlo":[{"sidlo":{"kodStatu":"CZ","nazevStatu":"Česká republika","kodKraje":116,"nazevKraje":"Jihomoravský kraj","kodOkresu":3713,"nazevOkresu":"Znojmo","kodObce":594920,"nazevObce":"Tasovice","cisloDomovni":275,"kodCastiObce":165123,"nazevCastiObce":"Tasovice","kodAdresnihoMista":10932305,"psc":67125,"textovaAdresa":"č.p. 275, 67125 Tasovice","standardizaceAdresy":true,"typCisloDomovni":1},"primarniZaznam":true}],"pravniForma":"112","pravniFormaRos":"112","datovyZdroj":"res"},{"obchodniJmeno":[{"obchodniJmeno":"VERASTO s.r.o.","primarniZaznam":true}],"sidlo":[{"sidlo":{"kodStatu":"CZ","nazevStatu":"Česká republika","kodKraje":116,"nazevKraje":"Jihomoravský kraj","kodOkresu":3713,"nazevOkresu":"Znojmo","kodObce":594920,"nazevObce":"Tasovice","cisloDomovni":275,"kodCastiObce":165123,"nazevCastiObce":"Tasovice","kodAdresnihoMista":10932305,"psc":67125,"textovaAdresa":"č.p. 275, 67125 Tasovice","standardizaceAdresy":true,"typCisloDomovni":1},"primarniZaznam":true}],"pravniFormaRos":"112","datovyZdroj":"ros"},{"obchodniJmeno":[{"obchodniJmeno":"VERASTO s.r.o.","primarniZaznam":true}],"sidlo":[{"sidlo":{"kodStatu":"CZ","nazevStatu":"Česká republika","kodKraje":116,"nazevKraje":"Jihomoravský kraj","kodOkresu":3713,"nazevOkresu":"Znojmo","kodObce":594920,"nazevObce":"Tasovice","cisloDomovni":275,"kodCastiObce":165123,"nazevCastiObce":"Tasovice","kodAdresnihoMista":10932305,"psc":67125,"textovaAdresa":"č.p. 275, 67125 Tasovice","standardizaceAdresy":true,"typCisloDomovni":1},"primarniZaznam":true}],"pravniForma":"112","datovyZdroj":"rzp"},{"obchodniJmeno":[{"obchodniJmeno":"VERASTO s.r.o.","primarniZaznam":true}],"sidlo":[{"sidlo":{"kodStatu":"CZ","nazevStatu":"Česká republika","kodKraje":116,"nazevKraje":"Jihomoravský kraj","kodOkresu":3713,"nazevOkresu":"Znojmo","kodObce":594920,"nazevObce":"Tasovice","cisloDomovni":275,"kodCastiObce":165123,"nazevCastiObce":"Tasovice","kodAdresnihoMista":10932305,"psc":67125,"textovaAdresa":"č.p. 275, 67125 Tasovice","standardizaceAdresy":true,"typCisloDomovni":1},"primarniZaznam":true}],"pravniForma":"112","spisovaZnacka":"C 100138/KSBR","datovyZdroj":"vr"}],"czNace":["461","49410","74990","82100","74200","33","855","73","58190","741","25","77220","952","255","47","69200","68200","00","28","46"]}