{
  "_export": {
    "schemaVersion": "1.0.0",
    "kind": "notification-candidates",
    "caseId": "DD-Able-CZ-2026-07-17",
    "generatedAt": "2026-07-18",
    "source": "static/data/dossier/snapshots/ (immutable manifests)",
    "note": "Každá materiální změna je objekt první třídy s vlastní trasou. Sémantické změny — nikdy rozdíly formátování, pořadí polí nebo času buildu."
  },
  "from_snapshot_id": "able-cz-public-2026-07-18-r07",
  "to_snapshot_id": "able-cz-public-2026-07-18-r08",
  "candidates": [
    {
      "change_id": "CHG-0363",
      "headline": "Explicitní řešení rozporu CON-01 (CFL-CON-01).",
      "materiality": "INFORMATIONAL",
      "object": "conflict_resolution:CFL-CON-01",
      "summary": "added conflict_resolution CFL-CON-01",
      "snapshot": "able-cz-public-2026-07-18-r08",
      "effective_at": null,
      "observed_at": null,
      "public_url": "/dossier/changes/",
      "should_notify": false,
      "notification_reason": "pod prahem notifikace (HIGH)"
    },
    {
      "change_id": "CHG-0364",
      "headline": "Explicitní řešení rozporu CON-02 (CFL-CON-02).",
      "materiality": "INFORMATIONAL",
      "object": "conflict_resolution:CFL-CON-02",
      "summary": "added conflict_resolution CFL-CON-02",
      "snapshot": "able-cz-public-2026-07-18-r08",
      "effective_at": null,
      "observed_at": null,
      "public_url": "/dossier/changes/",
      "should_notify": false,
      "notification_reason": "pod prahem notifikace (HIGH)"
    },
    {
      "change_id": "CHG-0365",
      "headline": "Explicitní řešení rozporu CON-03 (CFL-CON-03).",
      "materiality": "INFORMATIONAL",
      "object": "conflict_resolution:CFL-CON-03",
      "summary": "added conflict_resolution CFL-CON-03",
      "snapshot": "able-cz-public-2026-07-18-r08",
      "effective_at": null,
      "observed_at": null,
      "public_url": "/dossier/changes/",
      "should_notify": false,
      "notification_reason": "pod prahem notifikace (HIGH)"
    },
    {
      "change_id": "CHG-0366",
      "headline": "Nové exekutivní zjištění EXEC-01: Identita firmy je ověřena primárně proti úředním artefaktům; primární průchod přinesl podstatné korekce — mj. původní jméno BIT CONSULTING …",
      "materiality": "MEDIUM",
      "object": "executive_finding:EXEC-01",
      "summary": "added executive_finding EXEC-01",
      "snapshot": "able-cz-public-2026-07-18-r08",
      "effective_at": null,
      "observed_at": null,
      "public_url": "/dossier/changes/chg-0366/",
      "should_notify": false,
      "notification_reason": "pod prahem notifikace (HIGH)"
    },
    {
      "change_id": "CHG-0367",
      "headline": "Nové exekutivní zjištění EXEC-02: Největším společníkem není zakladatelská dvojice, ale ZenX Capital, a.s. — od října 2020 drží 45,8–50 %, víc než oba zakladatelé dohromady;…",
      "materiality": "MEDIUM",
      "object": "executive_finding:EXEC-02",
      "summary": "added executive_finding EXEC-02",
      "snapshot": "able-cz-public-2026-07-18-r08",
      "effective_at": null,
      "observed_at": null,
      "public_url": "/dossier/changes/chg-0367/",
      "should_notify": false,
      "notification_reason": "pod prahem notifikace (HIGH)"
    },
    {
      "change_id": "CHG-0368",
      "headline": "Nové exekutivní zjištění EXEC-03: Petr Faraga nebyl 'nově příchozí drobný společník', ale spoluzakladatel s třetinovým podílem a jednatel 2012–2020.",
      "materiality": "MEDIUM",
      "object": "executive_finding:EXEC-03",
      "summary": "added executive_finding EXEC-03",
      "snapshot": "able-cz-public-2026-07-18-r08",
      "effective_at": null,
      "observed_at": null,
      "public_url": "/dossier/changes/chg-0368/",
      "should_notify": false,
      "notification_reason": "pod prahem notifikace (HIGH)"
    },
    {
      "change_id": "CHG-0369",
      "headline": "Nové exekutivní zjištění EXEC-04: Able.cz má rejstříkově doložené dceřiné společnosti (Mindee app 95 %, Verzuz.com 100 %) a FaMe trade je aktivní s Václavem Faragou jako 50%…",
      "materiality": "MEDIUM",
      "object": "executive_finding:EXEC-04",
      "summary": "added executive_finding EXEC-04",
      "snapshot": "able-cz-public-2026-07-18-r08",
      "effective_at": null,
      "observed_at": null,
      "public_url": "/dossier/changes/chg-0369/",
      "should_notify": false,
      "notification_reason": "pod prahem notifikace (HIGH)"
    },
    {
      "change_id": "CHG-0370",
      "headline": "Nové exekutivní zjištění EXEC-05: Většina marketingových a výkonnostních tvrzení zůstává tvrzením firmy bez nezávislého potvrzení; oficiální registr smluv nevrací pro Able.c…",
      "materiality": "MEDIUM",
      "object": "executive_finding:EXEC-05",
      "summary": "added executive_finding EXEC-05",
      "snapshot": "able-cz-public-2026-07-18-r08",
      "effective_at": null,
      "observed_at": null,
      "public_url": "/dossier/changes/chg-0370/",
      "should_notify": false,
      "notification_reason": "pod prahem notifikace (HIGH)"
    },
    {
      "change_id": "CHG-0371",
      "headline": "Nové exekutivní zjištění EXEC-06: Podaná finanční trajektorie (tržby −14,8 % YoY, marže pod 2 %, společnické půjčky 3,1→10,0M CZK) je hluboko pod mediální růstovou narací ~1…",
      "materiality": "MEDIUM",
      "object": "executive_finding:EXEC-06",
      "summary": "added executive_finding EXEC-06",
      "snapshot": "able-cz-public-2026-07-18-r08",
      "effective_at": null,
      "observed_at": null,
      "public_url": "/dossier/changes/chg-0371/",
      "should_notify": false,
      "notification_reason": "pod prahem notifikace (HIGH)"
    },
    {
      "change_id": "CHG-0372",
      "headline": "Nové exekutivní zjištění EXEC-07: Rozpor v čísle spisu (CON-01) zůstává viditelný; CON-02 byl vyřešen primárním záznamem; přibyl CON-03 (mediální vs. rejstříkové datum Oslzl…",
      "materiality": "MEDIUM",
      "object": "executive_finding:EXEC-07",
      "summary": "added executive_finding EXEC-07",
      "snapshot": "able-cz-public-2026-07-18-r08",
      "effective_at": null,
      "observed_at": null,
      "public_url": "/dossier/changes/chg-0372/",
      "should_notify": false,
      "notification_reason": "pod prahem notifikace (HIGH)"
    },
    {
      "change_id": "CHG-0373",
      "headline": "Nové exekutivní zjištění EXEC-08: Důvěra je střední: vysoká u identity a vlastnictví (primárně ověřené), nízká u výkonnostních tvrzení; insolvenční screening zůstává BLOCKED…",
      "materiality": "MEDIUM",
      "object": "executive_finding:EXEC-08",
      "summary": "added executive_finding EXEC-08",
      "snapshot": "able-cz-public-2026-07-18-r08",
      "effective_at": null,
      "observed_at": null,
      "public_url": "/dossier/changes/chg-0373/",
      "should_notify": false,
      "notification_reason": "pod prahem notifikace (HIGH)"
    },
    {
      "change_id": "CHG-0374",
      "headline": "Deklarovaný předpoklad ASM-01: Podaná účetní závěrka (Sbírka listin) věrně zachycuje účetnictví subjektu tak, jak bylo podáno; nezávislý audit nebyl k…",
      "materiality": "INFORMATIONAL",
      "object": "reasoning_assumption:ASM-01",
      "summary": "added reasoning_assumption ASM-01",
      "snapshot": "able-cz-public-2026-07-18-r08",
      "effective_at": null,
      "observed_at": null,
      "public_url": "/dossier/changes/",
      "should_notify": false,
      "notification_reason": "pod prahem notifikace (HIGH)"
    },
    {
      "change_id": "CHG-0375",
      "headline": "Deklarovaný předpoklad ASM-02: Veřejný rejstřík (VR/ARES) je autoritativní pro právní skutečnosti (vlastnictví, funkce, data zápisu); mediální líčení …",
      "materiality": "INFORMATIONAL",
      "object": "reasoning_assumption:ASM-02",
      "summary": "added reasoning_assumption ASM-02",
      "snapshot": "able-cz-public-2026-07-18-r08",
      "effective_at": null,
      "observed_at": null,
      "public_url": "/dossier/changes/",
      "should_notify": false,
      "notification_reason": "pod prahem notifikace (HIGH)"
    },
    {
      "change_id": "CHG-0376",
      "headline": "Deklarovaný předpoklad ASM-03: Zachované artefakty (SHA-256, provider-runs) reprezentují stav zdroje v okamžiku stažení.",
      "materiality": "INFORMATIONAL",
      "object": "reasoning_assumption:ASM-03",
      "summary": "added reasoning_assumption ASM-03",
      "snapshot": "able-cz-public-2026-07-18-r08",
      "effective_at": null,
      "observed_at": null,
      "public_url": "/dossier/changes/",
      "should_notify": false,
      "notification_reason": "pod prahem notifikace (HIGH)"
    },
    {
      "change_id": "CHG-0377",
      "headline": "Deklarovaný předpoklad ASM-04: Mediální články citované jako SRC-04/SRC-05/SRC-22 přisuzují výroky uvedeným osobám správně.",
      "materiality": "INFORMATIONAL",
      "object": "reasoning_assumption:ASM-04",
      "summary": "added reasoning_assumption ASM-04",
      "snapshot": "able-cz-public-2026-07-18-r08",
      "effective_at": null,
      "observed_at": null,
      "public_url": "/dossier/changes/",
      "should_notify": false,
      "notification_reason": "pod prahem notifikace (HIGH)"
    },
    {
      "change_id": "CHG-0378",
      "headline": "Deklarovaný předpoklad ASM-05: Absence záznamu ve veřejném zdroji není důkazem absence ve skutečnosti (NOT_FOUND ≠ negativní fakt; BLOCKED ≠ NOT_FOUND…",
      "materiality": "INFORMATIONAL",
      "object": "reasoning_assumption:ASM-05",
      "summary": "added reasoning_assumption ASM-05",
      "snapshot": "able-cz-public-2026-07-18-r08",
      "effective_at": null,
      "observed_at": null,
      "public_url": "/dossier/changes/",
      "should_notify": false,
      "notification_reason": "pod prahem notifikace (HIGH)"
    },
    {
      "change_id": "CHG-0379",
      "headline": "Nový úsudkový řetězec INF-CLM-35 → CLM-35.",
      "materiality": "LOW",
      "object": "reasoning_inference:INF-CLM-35",
      "summary": "added reasoning_inference INF-CLM-35",
      "snapshot": "able-cz-public-2026-07-18-r08",
      "effective_at": null,
      "observed_at": null,
      "public_url": "/dossier/changes/",
      "should_notify": false,
      "notification_reason": "pod prahem notifikace (HIGH)"
    },
    {
      "change_id": "CHG-0380",
      "headline": "Nový úsudkový řetězec INF-CLM-38 → CLM-38.",
      "materiality": "LOW",
      "object": "reasoning_inference:INF-CLM-38",
      "summary": "added reasoning_inference INF-CLM-38",
      "snapshot": "able-cz-public-2026-07-18-r08",
      "effective_at": null,
      "observed_at": null,
      "public_url": "/dossier/changes/",
      "should_notify": false,
      "notification_reason": "pod prahem notifikace (HIGH)"
    },
    {
      "change_id": "CHG-0381",
      "headline": "Nový úsudkový řetězec INF-CLM-40 → CLM-40.",
      "materiality": "LOW",
      "object": "reasoning_inference:INF-CLM-40",
      "summary": "added reasoning_inference INF-CLM-40",
      "snapshot": "able-cz-public-2026-07-18-r08",
      "effective_at": null,
      "observed_at": null,
      "public_url": "/dossier/changes/",
      "should_notify": false,
      "notification_reason": "pod prahem notifikace (HIGH)"
    },
    {
      "change_id": "CHG-0382",
      "headline": "Nový úsudkový řetězec INF-CLM-43 → CLM-43.",
      "materiality": "LOW",
      "object": "reasoning_inference:INF-CLM-43",
      "summary": "added reasoning_inference INF-CLM-43",
      "snapshot": "able-cz-public-2026-07-18-r08",
      "effective_at": null,
      "observed_at": null,
      "public_url": "/dossier/changes/",
      "should_notify": false,
      "notification_reason": "pod prahem notifikace (HIGH)"
    },
    {
      "change_id": "CHG-0383",
      "headline": "Nový úsudkový řetězec INF-CLM-45 → CLM-45.",
      "materiality": "LOW",
      "object": "reasoning_inference:INF-CLM-45",
      "summary": "added reasoning_inference INF-CLM-45",
      "snapshot": "able-cz-public-2026-07-18-r08",
      "effective_at": null,
      "observed_at": null,
      "public_url": "/dossier/changes/",
      "should_notify": false,
      "notification_reason": "pod prahem notifikace (HIGH)"
    },
    {
      "change_id": "CHG-0384",
      "headline": "Nový úsudkový řetězec INF-CLM-48 → CLM-48.",
      "materiality": "LOW",
      "object": "reasoning_inference:INF-CLM-48",
      "summary": "added reasoning_inference INF-CLM-48",
      "snapshot": "able-cz-public-2026-07-18-r08",
      "effective_at": null,
      "observed_at": null,
      "public_url": "/dossier/changes/",
      "should_notify": false,
      "notification_reason": "pod prahem notifikace (HIGH)"
    },
    {
      "change_id": "CHG-0385",
      "headline": "Nový úsudkový řetězec INF-CLM-50 → CLM-50.",
      "materiality": "LOW",
      "object": "reasoning_inference:INF-CLM-50",
      "summary": "added reasoning_inference INF-CLM-50",
      "snapshot": "able-cz-public-2026-07-18-r08",
      "effective_at": null,
      "observed_at": null,
      "public_url": "/dossier/changes/",
      "should_notify": false,
      "notification_reason": "pod prahem notifikace (HIGH)"
    },
    {
      "change_id": "CHG-0386",
      "headline": "Nový úsudkový řetězec INF-CLM-51 → CLM-51.",
      "materiality": "LOW",
      "object": "reasoning_inference:INF-CLM-51",
      "summary": "added reasoning_inference INF-CLM-51",
      "snapshot": "able-cz-public-2026-07-18-r08",
      "effective_at": null,
      "observed_at": null,
      "public_url": "/dossier/changes/",
      "should_notify": false,
      "notification_reason": "pod prahem notifikace (HIGH)"
    },
    {
      "change_id": "CHG-0387",
      "headline": "Nový úsudkový řetězec INF-CLM-53 → CLM-53.",
      "materiality": "LOW",
      "object": "reasoning_inference:INF-CLM-53",
      "summary": "added reasoning_inference INF-CLM-53",
      "snapshot": "able-cz-public-2026-07-18-r08",
      "effective_at": null,
      "observed_at": null,
      "public_url": "/dossier/changes/",
      "should_notify": false,
      "notification_reason": "pod prahem notifikace (HIGH)"
    },
    {
      "change_id": "CHG-0388",
      "headline": "Nový úsudkový řetězec INF-CLM-56 → CLM-56.",
      "materiality": "LOW",
      "object": "reasoning_inference:INF-CLM-56",
      "summary": "added reasoning_inference INF-CLM-56",
      "snapshot": "able-cz-public-2026-07-18-r08",
      "effective_at": null,
      "observed_at": null,
      "public_url": "/dossier/changes/",
      "should_notify": false,
      "notification_reason": "pod prahem notifikace (HIGH)"
    },
    {
      "change_id": "CHG-0389",
      "headline": "Nový úsudkový řetězec INF-FIN-ASSESS-01 → FIN-ASSESS-01.",
      "materiality": "LOW",
      "object": "reasoning_inference:INF-FIN-ASSESS-01",
      "summary": "added reasoning_inference INF-FIN-ASSESS-01",
      "snapshot": "able-cz-public-2026-07-18-r08",
      "effective_at": null,
      "observed_at": null,
      "public_url": "/dossier/changes/",
      "should_notify": false,
      "notification_reason": "pod prahem notifikace (HIGH)"
    },
    {
      "change_id": "CHG-0390",
      "headline": "Nový úsudkový řetězec INF-FIN-ASSESS-02 → FIN-ASSESS-02.",
      "materiality": "LOW",
      "object": "reasoning_inference:INF-FIN-ASSESS-02",
      "summary": "added reasoning_inference INF-FIN-ASSESS-02",
      "snapshot": "able-cz-public-2026-07-18-r08",
      "effective_at": null,
      "observed_at": null,
      "public_url": "/dossier/changes/",
      "should_notify": false,
      "notification_reason": "pod prahem notifikace (HIGH)"
    },
    {
      "change_id": "CHG-0391",
      "headline": "Nový úsudkový řetězec INF-FIN-ASSESS-03 → FIN-ASSESS-03.",
      "materiality": "LOW",
      "object": "reasoning_inference:INF-FIN-ASSESS-03",
      "summary": "added reasoning_inference INF-FIN-ASSESS-03",
      "snapshot": "able-cz-public-2026-07-18-r08",
      "effective_at": null,
      "observed_at": null,
      "public_url": "/dossier/changes/",
      "should_notify": false,
      "notification_reason": "pod prahem notifikace (HIGH)"
    },
    {
      "change_id": "CHG-0392",
      "headline": "Nový úsudkový řetězec INF-FIN-ASSESS-04 → FIN-ASSESS-04.",
      "materiality": "LOW",
      "object": "reasoning_inference:INF-FIN-ASSESS-04",
      "summary": "added reasoning_inference INF-FIN-ASSESS-04",
      "snapshot": "able-cz-public-2026-07-18-r08",
      "effective_at": null,
      "observed_at": null,
      "public_url": "/dossier/changes/",
      "should_notify": false,
      "notification_reason": "pod prahem notifikace (HIGH)"
    },
    {
      "change_id": "CHG-0393",
      "headline": "Nový úsudkový řetězec INF-R-01 → R-01.",
      "materiality": "LOW",
      "object": "reasoning_inference:INF-R-01",
      "summary": "added reasoning_inference INF-R-01",
      "snapshot": "able-cz-public-2026-07-18-r08",
      "effective_at": null,
      "observed_at": null,
      "public_url": "/dossier/changes/",
      "should_notify": false,
      "notification_reason": "pod prahem notifikace (HIGH)"
    },
    {
      "change_id": "CHG-0394",
      "headline": "Nový úsudkový řetězec INF-R-02 → R-02.",
      "materiality": "LOW",
      "object": "reasoning_inference:INF-R-02",
      "summary": "added reasoning_inference INF-R-02",
      "snapshot": "able-cz-public-2026-07-18-r08",
      "effective_at": null,
      "observed_at": null,
      "public_url": "/dossier/changes/",
      "should_notify": false,
      "notification_reason": "pod prahem notifikace (HIGH)"
    },
    {
      "change_id": "CHG-0395",
      "headline": "Nový úsudkový řetězec INF-R-03 → R-03.",
      "materiality": "LOW",
      "object": "reasoning_inference:INF-R-03",
      "summary": "added reasoning_inference INF-R-03",
      "snapshot": "able-cz-public-2026-07-18-r08",
      "effective_at": null,
      "observed_at": null,
      "public_url": "/dossier/changes/",
      "should_notify": false,
      "notification_reason": "pod prahem notifikace (HIGH)"
    },
    {
      "change_id": "CHG-0396",
      "headline": "Nový úsudkový řetězec INF-R-04 → R-04.",
      "materiality": "LOW",
      "object": "reasoning_inference:INF-R-04",
      "summary": "added reasoning_inference INF-R-04",
      "snapshot": "able-cz-public-2026-07-18-r08",
      "effective_at": null,
      "observed_at": null,
      "public_url": "/dossier/changes/",
      "should_notify": false,
      "notification_reason": "pod prahem notifikace (HIGH)"
    },
    {
      "change_id": "CHG-0397",
      "headline": "Nový úsudkový řetězec INF-R-05 → R-05.",
      "materiality": "LOW",
      "object": "reasoning_inference:INF-R-05",
      "summary": "added reasoning_inference INF-R-05",
      "snapshot": "able-cz-public-2026-07-18-r08",
      "effective_at": null,
      "observed_at": null,
      "public_url": "/dossier/changes/",
      "should_notify": false,
      "notification_reason": "pod prahem notifikace (HIGH)"
    },
    {
      "change_id": "CHG-0398",
      "headline": "Nový úsudkový řetězec INF-R-06 → R-06.",
      "materiality": "LOW",
      "object": "reasoning_inference:INF-R-06",
      "summary": "added reasoning_inference INF-R-06",
      "snapshot": "able-cz-public-2026-07-18-r08",
      "effective_at": null,
      "observed_at": null,
      "public_url": "/dossier/changes/",
      "should_notify": false,
      "notification_reason": "pod prahem notifikace (HIGH)"
    }
  ]
}
